README.md
setup.py
dwhutils/DataVaultLoader.py
dwhutils/Docker.py
dwhutils/ILoader.py
dwhutils/Logger.py
dwhutils/MongoLoader.py
dwhutils/ReadEntity.py
dwhutils/TableReader.py
dwhutils/TechFields.py
dwhutils/Usert.py
dwhutils/__init__.py
dwhutils/build_dynamic_lookup.py
dwhutils/build_static_lookup.py
dwhutils/db_connection.py
dwhutils/db_loader.py
dwhutils/db_loader_alt.py
dwhutils/job.py
dwhutils/load_config.py
dwhutils/loader.py
dwhutils/lookup.py
dwhutils/mque.py
dwhutils/mque_put.py
dwhutils/utils.py
dwhutils.egg-info/PKG-INFO
dwhutils.egg-info/SOURCES.txt
dwhutils.egg-info/dependency_links.txt
dwhutils.egg-info/requires.txt
dwhutils.egg-info/top_level.txt