Metadata-Version: 1.0
Name: dwhutils
Version: 0.2.9
Summary: get utils for bitemporal data warehousing with mariadb
Home-page: UNKNOWN
Author: PoeticDrunkenCat
Author-email: poeticdrunkencat@gmail.com
License: UNKNOWN
Platform: UNKNOWN
